attgen/__init__.py
attgen/__main__.py
attgen/generate.py
attgen/pdf_reference.py
attgen/read_yaml.py
attgen/settings.py
attgen-1.1.0.dist-info/LICENSE-APACHE
attgen-1.1.0.dist-info/METADATA
attgen-1.1.0.dist-info/WHEEL
attgen-1.1.0.dist-info/entry_points.txt
attgen-1.1.0.dist-info/top_level.txt
attgen-1.1.0.dist-info/RECORD
